odoo/addons/easy_my_coop_api_logs/README.rst
odoo/addons/easy_my_coop_api_logs/__init__.py
odoo/addons/easy_my_coop_api_logs/__manifest__.py
odoo/addons/easy_my_coop_api_logs/i18n/easy_my_coop_api_logs.pot
odoo/addons/easy_my_coop_api_logs/models/__init__.py
odoo/addons/easy_my_coop_api_logs/models/emc_api_log.py
odoo/addons/easy_my_coop_api_logs/readme/CONTRIBUTORS.rst
odoo/addons/easy_my_coop_api_logs/readme/DESCRIPTION.rst
odoo/addons/easy_my_coop_api_logs/security/ir.model.access.csv
odoo/addons/easy_my_coop_api_logs/static/description/index.html
odoo/addons/easy_my_coop_api_logs/views/emc_api_log_views.xml
odoo12_addon_easy_my_coop_api_logs-12.0.0.0.1.99.dev1.dist-info/METADATA
odoo12_addon_easy_my_coop_api_logs-12.0.0.0.1.99.dev1.dist-info/WHEEL
odoo12_addon_easy_my_coop_api_logs-12.0.0.0.1.99.dev1.dist-info/top_level.txt
odoo12_addon_easy_my_coop_api_logs-12.0.0.0.1.99.dev1.dist-info/RECORD
