Metadata-Version: 2.1
Name: odoo12-addon-easy-my-coop-api-logs
Version: 12.0.0.0.1.99.dev1
Summary: Helpers to log calls in and out of easy_my_coop_api.
Home-page: https://coopiteasy.be
Author: Coop IT Easy SCRLfs
License: AGPL-3
Platform: UNKNOWN
Classifier: Programming Language :: Python
Classifier: Framework :: Odoo
Classifier: Framework :: Odoo :: 12.0
Classifier: License :: OSI Approved :: GNU Affero General Public License v3
Requires-Python: >=3.5
Requires-Dist: odoo (<12.1dev,>=12.0a)
